addresses/__init__.py
addresses/admin.py
addresses/apps.py
addresses/mixins.py
addresses/models.py
addresses/parsers.py
addresses/serializers.py
addresses/urls.py
addresses/views.py
addresses/management/__init__.py
addresses/management/commands/__init__.py
addresses/management/commands/address_loaddata.py
addresses/migrations/0001_initial.py
addresses/migrations/0002_state.py
addresses/migrations/0003_city.py
addresses/migrations/0004_neighborhood.py
addresses/migrations/0005_streettype.py
addresses/migrations/0006_street.py
addresses/migrations/0007_auto_20181015_1751.py
addresses/migrations/0008_auto_20181015_1826.py
addresses/migrations/__init__.py
addresses/templates/addresses/get_delivery_price.xml
addresses/templates/addresses/get_street_by_zipcode.xml
django_brazilian_addresses-0.2.dist-info/LICENSE
django_brazilian_addresses-0.2.dist-info/METADATA
django_brazilian_addresses-0.2.dist-info/WHEEL
django_brazilian_addresses-0.2.dist-info/top_level.txt
django_brazilian_addresses-0.2.dist-info/RECORD
